shmgpsd.py
shmgpsd-0.3.4.dist-info/LICENSE
shmgpsd-0.3.4.dist-info/METADATA
shmgpsd-0.3.4.dist-info/WHEEL
shmgpsd-0.3.4.dist-info/top_level.txt
shmgpsd-0.3.4.dist-info/RECORD
