Metadata-Version: 2.1
Name: shmgpsd
Version: 0.3.4
Summary: GPSD shared memory tool
Author-email: Fernilab <support@fernilab.com>
Maintainer-email: Fernilab <support@fernilab.com>
Project-URL: Homepage, https://fernilab.com
Project-URL: Repository, https://github.com/fernilab/shmgpsd.git
License-File: LICENSE
